_muGrid.cpython-39-x86_64-linux-gnu.so
_muFFT.cpython-39-x86_64-linux-gnu.so
_muSpectre.cpython-39-x86_64-linux-gnu.so
.muspectre.mesonpy.libs/libmuFFT.so
.muspectre.mesonpy.libs/libmuGrid.so
.muspectre.mesonpy.libs/libmuSpectre.so
muspectre-0.27.0.data/purelib/muFFT/__init__.py
muspectre-0.27.0.data/purelib/muFFT/Stencils2D.py
muspectre-0.27.0.data/purelib/muFFT/Stencils1D.py
muspectre-0.27.0.data/purelib/muFFT/NetCDF.py
muspectre-0.27.0.data/purelib/muFFT/Stencils3D.py
muspectre-0.27.0.data/purelib/muGrid/Parallel.py
muspectre-0.27.0.data/purelib/muGrid/__init__.py
muspectre-0.27.0.data/purelib/muSpectre/sensitivity_analysis.py
muspectre-0.27.0.data/purelib/muSpectre/eshelby_slow.py
muspectre-0.27.0.data/purelib/muSpectre/__init__.py
muspectre-0.27.0.data/purelib/muSpectre/linear_finite_elements.py
muspectre-0.27.0.data/purelib/muSpectre/stochastic_plasticity_search.py
muspectre-0.27.0.data/purelib/muSpectre/vtk_export.py
muspectre-0.27.0.data/purelib/muSpectre/gradient_integration.py
muspectre-0.27.0.dist-info/LICENSE
muspectre-0.27.0.dist-info/RECORD
muspectre-0.27.0.dist-info/METADATA
muspectre-0.27.0.dist-info/WHEEL
