Metadata-Version: 2.1
Name: muSpectre
Version: 0.27.0
Summary: µSpectre is an open-source platform for efficient FFT-based continuum mesoscale modelling
Author-Email: Till Junge <till.junge@altermail.ch>, Lars Pastewka <lars.pastewka@imtek.uni-freiburg.de>, Ali Falsafi <ali.falsafi@epfl.ch>, Richard Leute <richard.leute@imtek.uni-freiburg.de>
License:                    GNU LESSER GENERAL PUBLIC LICENSE
Classifier: Development Status :: 5 - Production/Stable
Classifier: Programming Language :: Python
Project-URL: Documentation, https://muspectre.gitlab.io/muspectre/index.html
Project-URL: Repository, https://gitlab.com/muspectre/muspectre
Project-URL: Changelog, https://gitlab.com/muspectre/muspectre/-/blob/master/CHANGELOG.md
Requires-Python: >=3.5.0
Requires-Dist: scipy
Requires-Dist: uvw
Requires-Dist: meshio
Requires-Dist: h5py
Requires-Dist: pytest; extra == "test"
Requires-Dist: pytest-cov; extra == "test"
Provides-Extra: test
